metaworkspace/__init__.py
metaworkspace/__main__.py
metaworkspace/init.py
metaworkspace/install.py
metaworkspace/run.py
metaworkspace/tree.py
metaworkspace/workspace.py
metaworkspace/api/__init__.py
metaworkspace/api/api.py
metaworkspace/api/project.py
metaworkspace/api/workspace.py
metaworkspace-0.0.3.dist-info/METADATA
metaworkspace-0.0.3.dist-info/WHEEL
metaworkspace-0.0.3.dist-info/top_level.txt
metaworkspace-0.0.3.dist-info/RECORD
